bseindia/__init__.py
bseindia/constants.py
bseindia/get_data.py
bseindia/libutil.py
bseindia/logger.py
bseindia-0.1.dist-info/LICENSE
bseindia-0.1.dist-info/METADATA
bseindia-0.1.dist-info/WHEEL
bseindia-0.1.dist-info/top_level.txt
bseindia-0.1.dist-info/RECORD
