Metadata-Version: 2.1
Name: bseindia
Version: 0.1
Summary: library to get BSE India data
Home-page: https://github.com/RuchiTanmay/bseindia
Author: RuchiTanmay
Author-email: ruchitanmay@gmail.com
Keywords: bseindia,bse,python,sdk,trading,stock markets
Classifier: Intended Audience :: Developers
Classifier: Natural Language :: English
Classifier: Operating System :: OS Independent
Classifier: Programming Language :: Python
Classifier: Programming Language :: Python :: 3.9
Classifier: Programming Language :: Python :: Implementation :: PyPy
Classifier: Topic :: Software Development :: Libraries :: Python Modules
License-File: LICENSE
Requires-Dist: requests
Requires-Dist: pandas
